.gitignore
AUTHORS
COPYING
MANIFEST.in
README.rst
setup.py
iwlib/__init__.py
iwlib/_iwlib_build.py
iwlib/iwconfig.py
iwlib/iwlist.py
iwlib/utils.py
iwlib.egg-info/PKG-INFO
iwlib.egg-info/SOURCES.txt
iwlib.egg-info/dependency_links.txt
iwlib.egg-info/not-zip-safe
iwlib.egg-info/requires.txt
iwlib.egg-info/top_level.txt
iwlib/__pycache__/_cffi__x936037faxaad18ffc.c
iwlib/__pycache__/_cffi__xdea6f476xaad18ffc.c
test/__init__.py
test/test_imports.py