Metadata-Version: 1.1
Name: iwlib
Version: 1.7.0
Summary: Python module to interface with iwlib
Home-page: https://github.com/nhoad/python-iwlib
Author: Nathan Hoad
Author-email: nathan@hoad.io
License: GPLv2
Platform: UNKNOWN
Classifier: Intended Audience :: Developers
Classifier: Natural Language :: English
Classifier: License :: OSI Approved :: GNU General Public License v2 (GPLv2)
Classifier: Programming Language :: Python
Classifier: Programming Language :: Python :: 3
Classifier: Programming Language :: Python :: Implementation :: PyPy
Classifier: Programming Language :: Python :: Implementation :: CPython
